raspberry_config_sdk/BootConfig.py
raspberry_config_sdk/__init__.py
raspberry_config_sdk/utils.py
test/__init__.py
test/test_boot_config.py
raspberry_config_sdk-1.0.2.dist-info/LICENSE
raspberry_config_sdk-1.0.2.dist-info/METADATA
raspberry_config_sdk-1.0.2.dist-info/WHEEL
raspberry_config_sdk-1.0.2.dist-info/top_level.txt
raspberry_config_sdk-1.0.2.dist-info/RECORD
