Metadata-Version: 2.1
Name: raspberry-config-sdk
Version: 1.0.2
Summary: Easily Configure your Raspberry Pi from your code
Home-page: https://github.com/DEADSEC-SECURITY/raspberry-config-sdk
Author: DeadSec-Security
Author-email: amng835@gmail.com
License: MIT
Keywords: raspberry,raspberry pi,config.txt,raspberry config,boot
Requires-Python: >=3.8,==3.11.2
License-File: LICENSE
Requires-Dist: tqdm ~=4.66.0
Requires-Dist: bigtree ~=0.17.0
